Workbook

Sheet Pipeline
A1: Lead ID | B1: Company Name | C1: Industry | D1: Company Size | E1: Contact Name | F1: Contact Title | G1: Email | H1: Lead Source | I1: Date Created | J1: Sales Rep | K1: Budget Score | L1: Authority Score | M1: Need Score | N1: Timeline Score | O1: BANT Total | P1: Qualified? (15+) | Q1: Stage | R1: Deal Value (INR) | S1: Win Probability % | T1: Weighted Value (INR) | U1: Expected Close Date | V1: Actual Close Date | W1: Days in Pipeline | X1: Lost Reason
A2: LD2001 | B2: Vertex Traders | C2: Retail | D2: Small (1-50) | E2: Tanya | F2: VP Sales | G2: tanya@vertex.com | H2: Partner Channel | I2: 28-11-2025 | J2: Divya Nair | K2: 5 | L2: 3 | M2: 4 | N2: 4 | O2: =SUM(K2:N2) -> 16 | P2: =IF(O2>=15,"Yes","No") -> Yes | Q2: Closed Won | R2: 194000 | S2: 1 | T2: =R2*S2 -> 194000 | U2: 14-01-2026 | V2: 07-01-2026 | W2: 40
A3: LD2002 | B3: Bluepeak Retail | C3: FMCG | D3: Small (1-50) | E3: Kabir | F3: Procurement Manager | G3: kabir@bluepeak.com | H3: Referral | I3: 11-02-2026 | J3: Rohit Malhotra | K3: 4 | L3: 4 | M3: 5 | N3: 4 | O3: =SUM(K3:N3) -> 17 | P3: =IF(O3>=15,"Yes","No") -> Yes | Q3: Closed Lost | R3: 229000 | S3: 0 | T3: =R3*S3 -> 0 | U3: 17-04-2026 | V3: 23-03-2026 | W3: 40 | X3: Budget too high
A4: LD2003 | B4: Bluepeak Solutions | C4: Healthcare | D4: Mid-Market (51-500) | E4: Pooja | F4: COO | G4: pooja@bluepeak.com | H4: LinkedIn Outreach | I4: 14-03-2026 | J4: Sneha Iyer | K4: 1 | L4: 2 | M4: 3 | N4: 2 | O4: =SUM(K4:N4) -> 8 | P4: =IF(O4>=15,"Yes","No") -> No | Q4: Contacted | R4: 578000 | S4: 0.15 | T4: =R4*S4 -> 86700 | U4: 18-04-2026
A5: LD2004 | B5: Crestline Enterprises | C5: Retail | D5: Enterprise (500+) | E5: Kavya | F5: Procurement Manager | G5: kavya@crestline.com | H5: Inbound - Website | I5: 05-04-2026 | J5: Karan Bhatia | K5: 4 | L5: 3 | M5: 3 | N5: 3 | O5: =SUM(K5:N5) -> 13 | P5: =IF(O5>=15,"Yes","No") -> No | Q5: Proposal Sent | R5: 3009000 | S5: 0.55 | T5: =R5*S5 -> 1654950 | U5: 16-06-2026
A6: LD2005 | B6: Nova Mart | C6: E-commerce | D6: Small (1-50) | E6: Kavya | F6: Founder/CEO | G6: kavya@nova.com | H6: Referral | I6: 13-04-2026 | J6: Ananya Kapoor | K6: 4 | L6: 2 | M6: 5 | N6: 4 | O6: =SUM(K6:N6) -> 15 | P6: =IF(O6>=15,"Yes","No") -> Yes | Q6: Closed Lost | R6: 213000 | S6: 0 | T6: =R6*S6 -> 0 | U6: 25-05-2026 | V6: 02-05-2026 | W6: 19 | X6: Not enough authority to buy
A7: LD2006 | B7: Summit Solutions | C7: E-commerce | D7: Small (1-50) | E7: Zara | F7: COO | G7: zara@summit.com | H7: Cold Outbound | I7: 30-04-2025 | J7: Rohit Malhotra | K7: 1 | L7: 1 | M7: 1 | N7: 1 | O7: =SUM(K7:N7) -> 4 | P7: =IF(O7>=15,"Yes","No") -> No | Q7: Closed Lost | R7: 191000 | S7: 0 | T7: =R7*S7 -> 0 | U7: 14-07-2025 | V7: 14-05-2025 | W7: 14 | X7: Not enough authority to buy
A8: LD2007 | B8: Ember Ventures | C8: Retail | D8: Small (1-50) | E8: Ishita | F8: Procurement Manager | G8: ishita@ember.com | H8: Partner Channel | I8: 25-01-2026 | J8: Rohit Malhotra | K8: 5 | L8: 3 | M8: 3 | N8: 5 | O8: =SUM(K8:N8) -> 16 | P8: =IF(O8>=15,"Yes","No") -> Yes | Q8: Closed Won | R8: 202000 | S8: 1 | T8: =R8*S8 -> 202000 | U8: 22-02-2026 | V8: 03-03-2026 | W8: 37
A9: LD2008 | B9: Northstar Traders | C9: FMCG | D9: Small (1-50) | E9: Dev | F9: VP Sales | G9: dev@northstar.com | H9: Cold Outbound | I9: 06-02-2026 | J9: Karan Bhatia | K9: 1 | L9: 1 | M9: 3 | N9: 1 | O9: =SUM(K9:N9) -> 6 | P9: =IF(O9>=15,"Yes","No") -> No | Q9: Contacted | R9: 178000 | S9: 0.15 | T9: =R9*S9 -> 26700 | U9: 26-03-2026
A10: LD2009 | B10: Ironclad Industries | C10: Retail | D10: Small (1-50) | E10: Arjun | F10: COO | G10: arjun@ironclad.com | H10: Referral | I10: 15-04-2025 | J10: Sneha Iyer | K10: 5 | L10: 4 | M10: 5 | N10: 4 | O10: =SUM(K10:N10) -> 18 | P10: =IF(O10>=15,"Yes","No") -> Yes | Q10: Contacted | R10: 156000 | S10: 0.15 | T10: =R10*S10 -> 23400 | U10: 13-06-2025
A11: LD2010 | B11: Ember Industries | C11: FMCG | D11: Small (1-50) | E11: Aarav | F11: Marketing Director | G11: aarav@ember.com | H11: Cold Outbound | I11: 08-01-2026 | J11: Karan Bhatia | K11: 1 | L11: 3 | M11: 4 | N11: 1 | O11: =SUM(K11:N11) -> 9 | P11: =IF(O11>=15,"Yes","No") -> No | Q11: Qualified | R11: 196000 | S11: 0.35 | T11: =R11*S11 -> 68600 | U11: 27-02-2026
A12: LD2011 | B12: Redshift Enterprises | C12: Retail | D12: Mid-Market (51-500) | E12: Riya | F12: COO | G12: riya@redshift.com | H12: Inbound - Website | I12: 06-01-2026 | J12: Divya Nair | K12: 3 | L12: 2 | M12: 5 | N12: 3 | O12: =SUM(K12:N12) -> 13 | P12: =IF(O12>=15,"Yes","No") -> No | Q12: Contacted | R12: 891000 | S12: 0.15 | T12: =R12*S12 -> 133650 | U12: 11-02-2026
A13: LD2012 | B13: Ironclad Group | C13: E-commerce | D13: Mid-Market (51-500) | E13: Kabir | F13: Procurement Manager | G13: kabir@ironclad.com | H13: Cold Outbound | I13: 17-08-2025 | J13: Rohit Malhotra | K13: 1 | L13: 2 | M13: 2 | N13: 1 | O13: =SUM(K13:N13) -> 6 | P13: =IF(O13>=15,"Yes","No") -> No | Q13: Contacted | R13: 587000 | S13: 0.15 | T13: =R13*S13 -> 88050 | U13: 28-10-2025
A14: LD2013 | B14: Foxglove Enterprises | C14: Education | D14: Enterprise (500+) | E14: Kavya | F14: Head of Operations | G14: kavya@foxglove.com | H14: LinkedIn Outreach | I14: 31-12-2025 | J14: Karan Bhatia | K14: 2 | L14: 3 | M14: 2 | N14: 1 | O14: =SUM(K14:N14) -> 8 | P14: =IF(O14>=15,"Yes","No") -> No | Q14: Contacted | R14: 2711000 | S14: 0.15 | T14: =R14*S14 -> 406650 | U14: 17-02-2026
A15: LD2014 | B15: Cobalt Enterprises | C15: E-commerce | D15: Mid-Market (51-500) | E15: Vivaan | F15: Head of Operations | G15: vivaan@cobalt.com | H15: Referral | I15: 14-08-2025 | J15: Karan Bhatia | K15: 3 | L15: 4 | M15: 3 | N15: 3 | O15: =SUM(K15:N15) -> 13 | P15: =IF(O15>=15,"Yes","No") -> No | Q15: Contacted | R15: 614000 | S15: 0.15 | T15: =R15*S15 -> 92100 | U15: 03-10-2025
A16: LD2015 | B16: Nova Industries | C16: FMCG | D16: Mid-Market (51-500) | E16: Yash | F16: Founder/CEO | G16: yash@nova.com | H16: LinkedIn Outreach | I16: 02-02-2026 | J16: Rohit Malhotra | K16: 2 | L16: 1 | M16: 4 | N16: 2 | O16: =SUM(K16:N16) -> 9 | P16: =IF(O16>=15,"Yes","No") -> No | Q16: Closed Lost | R16: 824000 | S16: 0 | T16: =R16*S16 -> 0 | U16: 02-03-2026 | V16: 03-03-2026 | W16: 29 | X16: Budget too high
A17: LD2016 | B17: Lumen Group | C17: FMCG | D17: Small (1-50) | E17: Kabir | F17: VP Sales | G17: kabir@lumen.com | H17: LinkedIn Outreach | I17: 01-05-2026 | J17: Rohit Malhotra | K17: 1 | L17: 4 | M17: 2 | N17: 2 | O17: =SUM(K17:N17) -> 9 | P17: =IF(O17>=15,"Yes","No") -> No | Q17: Contacted | R17: 214000 | S17: 0.15 | T17: =R17*S17 -> 32100 | U17: 29-05-2026
A18: LD2017 | B18: Foxglove Enterprises | C18: Logistics | D18: Mid-Market (51-500) | E18: Yash | F18: Growth Lead | G18: yash@foxglove.com | H18: Inbound - Website | I18: 15-09-2025 | J18: Sneha Iyer | K18: 3 | L18: 1 | M18: 4 | N18: 4 | O18: =SUM(K18:N18) -> 12 | P18: =IF(O18>=15,"Yes","No") -> No | Q18: Contacted | R18: 550000 | S18: 0.15 | T18: =R18*S18 -> 82500 | U18: 08-10-2025
A19: LD2018 | B19: Nova Industries | C19: FMCG | D19: Small (1-50) | E19: Riya | F19: Founder/CEO | G19: riya@nova.com | H19: Referral | I19: 29-05-2026 | J19: Karan Bhatia | K19: 3 | L19: 4 | M19: 5 | N19: 3 | O19: =SUM(K19:N19) -> 15 | P19: =IF(O19>=15,"Yes","No") -> Yes | Q19: New Lead | R19: 185000 | S19: 0.05 | T19: =R19*S19 -> 9250 | U19: 26-07-2026
A20: LD2019 | B20: Summit Retail | C20: Retail | D20: Small (1-50) | E20: Tanya | F20: Marketing Director | G20: tanya@summit.com | H20: Cold Outbound | I20: 30-04-2026 | J20: Divya Nair | K20: 3 | L20: 2 | M20: 2 | N20: 2 | O20: =SUM(K20:N20) -> 9 | P20: =IF(O20>=15,"Yes","No") -> No | Q20: Contacted | R20: 136000 | S20: 0.15 | T20: =R20*S20 -> 20400 | U20: 26-05-2026
A21: LD2020 | B21: Ember Solutions | C21: FMCG | D21: Small (1-50) | E21: Yash | F21: Procurement Manager | G21: yash@ember.com | H21: Referral | I21: 11-10-2025 | J21: Ananya Kapoor | K21: 3 | L21: 1 | M21: 4 | N21: 3 | O21: =SUM(K21:N21) -> 11 | P21: =IF(O21>=15,"Yes","No") -> No | Q21: Qualified | R21: 206000 | S21: 0.35 | T21: =R21*S21 -> 72100 | U21: 12-11-2025
A22: LD2021 | B22: Palm Industries | C22: Healthcare | D22: Enterprise (500+) | E22: Zara | F22: Head of Operations | G22: zara@palm.com | H22: LinkedIn Outreach | I22: 11-09-2025 | J22: Sneha Iyer | K22: 2 | L22: 2 | M22: 1 | N22: 3 | O22: =SUM(K22:N22) -> 8 | P22: =IF(O22>=15,"Yes","No") -> No | Q22: New Lead | R22: 1970000 | S22: 0.05 | T22: =R22*S22 -> 98500 | U22: 13-10-2025
A23: LD2022 | B23: Zenith Enterprises | C23: E-commerce | D23: Small (1-50) | E23: Aditya | F23: IT Manager | G23: aditya@zenith.com | H23: Cold Outbound | I23: 06-02-2026 | J23: Ananya Kapoor | K23: 1 | L23: 2 | M23: 2 | N23: 2 | O23: =SUM(K23:N23) -> 7 | P23: =IF(O23>=15,"Yes","No") -> No | Q23: Contacted | R23: 139000 | S23: 0.15 | T23: =R23*S23 -> 20850 | U23: 16-04-2026
A24: LD2023 | B24: Driftwood Group | C24: Hospitality | D24: Small (1-50) | E24: Riya | F24: Growth Lead | G24: riya@driftwood.com | H24: Partner Channel | I24: 21-05-2025 | J24: Karan Bhatia | K24: 5 | L24: 4 | M24: 5 | N24: 3 | O24: =SUM(K24:N24) -> 17 | P24: =IF(O24>=15,"Yes","No") -> Yes | Q24: New Lead | R24: 234000 | S24: 0.05 | T24: =R24*S24 -> 11700 | U24: 20-06-2025
A25: LD2024 | B25: Meridian Traders | C25: E-commerce | D25: Small (1-50) | E25: Vivaan | F25: IT Manager | G25: vivaan@meridian.com | H25: Inbound - Website | I25: 18-02-2026 | J25: Sneha Iyer | K25: 4 | L25: 2 | M25: 3 | N25: 4 | O25: =SUM(K25:N25) -> 13 | P25: =IF(O25>=15,"Yes","No") -> No | Q25: Closed Won | R25: 154000 | S25: 1 | T25: =R25*S25 -> 154000 | U25: 17-03-2026 | V25: 23-03-2026 | W25: 33
A26: LD2025 | B26: Driftwood Solutions | C26: E-commerce | D26: Mid-Market (51-500) | E26: Nikhil | F26: Founder/CEO | G26: nikhil@driftwood.com | H26: Referral | I26: 06-10-2025 | J26: Rohit Malhotra | K26: 4 | L26: 4 | M26: 3 | N26: 5 | O26: =SUM(K26:N26) -> 16 | P26: =IF(O26>=15,"Yes","No") -> Yes | Q26: New Lead | R26: 544000 | S26: 0.05 | T26: =R26*S26 -> 27200 | U26: 19-12-2025
A27: LD2026 | B27: Willow Group | C27: Retail | D27: Small (1-50) | E27: Vivaan | F27: IT Manager | G27: vivaan@willow.com | H27: LinkedIn Outreach | I27: 22-05-2026 | J27: Rohit Malhotra | K27: 3 | L27: 1 | M27: 4 | N27: 2 | O27: =SUM(K27:N27) -> 10 | P27: =IF(O27>=15,"Yes","No") -> No | Q27: Qualified | R27: 236000 | S27: 0.35 | T27: =R27*S27 -> 82600 | U27: 16-06-2026
A28: LD2027 | B28: Orbit Industries | C28: FMCG | D28: Small (1-50) | E28: Arjun | F28: VP Sales | G28: arjun@orbit.com | H28: Cold Outbound | I28: 05-05-2025 | J28: Sneha Iyer | K28: 3 | L28: 2 | M28: 1 | N28: 1 | O28: =SUM(K28:N28) -> 7 | P28: =IF(O28>=15,"Yes","No") -> No | Q28: Contacted | R28: 242000 | S28: 0.15 | T28: =R28*S28 -> 36300 | U28: 09-06-2025
A29: LD2028 | B29: Havenly Retail | C29: E-commerce | D29: Small (1-50) | E29: Arjun | F29: VP Sales | G29: arjun@havenly.com | H29: Inbound - Website | I29: 05-07-2025 | J29: Rohit Malhotra | K29: 3 | L29: 2 | M29: 2 | N29: 3 | O29: =SUM(K29:N29) -> 10 | P29: =IF(O29>=15,"Yes","No") -> No | Q29: Contacted | R29: 196000 | S29: 0.15 | T29: =R29*S29 -> 29400 | U29: 11-08-2025
A30: LD2029 | B30: Ironclad Ventures | C30: Hospitality | D30: Mid-Market (51-500) | E30: Sana | F30: Marketing Director | G30: sana@ironclad.com | H30: Referral | I30: 16-01-2025 | J30: Divya Nair | K30: 2 | L30: 4 | M30: 3 | N30: 5 | O30: =SUM(K30:N30) -> 14 | P30: =IF(O30>=15,"Yes","No") -> No | Q30: Qualified | R30: 569000 | S30: 0.35 | T30: =R30*S30 -> 199150 | U30: 11-03-2025
A31: LD2030 | B31: Zenith Retail | C31: Logistics | D31: Mid-Market (51-500) | E31: Vivaan | F31: IT Manager | G31: vivaan@zenith.com | H31: Inbound - Website | I31: 24-08-2025 | J31: Rohit Malhotra | K31: 2 | L31: 1 | M31: 2 | N31: 2 | O31: =SUM(K31:N31) -> 7 | P31: =IF(O31>=15,"Yes","No") -> No | Q31: Contacted | R31: 678000 | S31: 0.15 | T31: =R31*S31 -> 101700 | U31: 05-11-2025
A32: LD2031 | B32: Anchor Retail | C32: Education | D32: Small (1-50) | E32: Yash | F32: Founder/CEO | G32: yash@anchor.com | H32: Inbound - Website | I32: 18-03-2026 | J32: Divya Nair | K32: 3 | L32: 1 | M32: 3 | N32: 4 | O32: =SUM(K32:N32) -> 11 | P32: =IF(O32>=15,"Yes","No") -> No | Q32: Contacted | R32: 211000 | S32: 0.15 | T32: =R32*S32 -> 31650 | U32: 21-05-2026
A33: LD2032 | B33: Crestline Group | C33: E-commerce | D33: Small (1-50) | E33: Ishita | F33: IT Manager | G33: ishita@crestline.com | H33: Inbound - Website | I33: 11-06-2025 | J33: Sneha Iyer | K33: 5 | L33: 4 | M33: 3 | N33: 4 | O33: =SUM(K33:N33) -> 16 | P33: =IF(O33>=15,"Yes","No") -> Yes | Q33: New Lead | R33: 169000 | S33: 0.05 | T33: =R33*S33 -> 8450 | U33: 05-08-2025
A34: LD2033 | B34: Anchor Solutions | C34: E-commerce | D34: Small (1-50) | E34: Tanya | F34: Head of Operations | G34: tanya@anchor.com | H34: Inbound - Website | I34: 12-08-2025 | J34: Karan Bhatia | K34: 4 | L34: 4 | M34: 2 | N34: 3 | O34: =SUM(K34:N34) -> 13 | P34: =IF(O34>=15,"Yes","No") -> No | Q34: Closed Lost | R34: 249000 | S34: 0 | T34: =R34*S34 -> 0 | U34: 02-09-2025 | V34: 21-09-2025 | W34: 40 | X34: Budget too high
A35: LD2034 | B35: Quartz Industries | C35: Healthcare | D35: Mid-Market (51-500) | E35: Sana | F35: Founder/CEO | G35: sana@quartz.com | H35: LinkedIn Outreach | I35: 08-06-2025 | J35: Karan Bhatia | K35: 2 | L35: 3 | M35: 2 | N35: 2 | O35: =SUM(K35:N35) -> 9 | P35: =IF(O35>=15,"Yes","No") -> No | Q35: New Lead | R35: 905000 | S35: 0.05 | T35: =R35*S35 -> 45250 | U35: 13-08-2025
A36: LD2035 | B36: Redshift Industries | C36: FMCG | D36: Mid-Market (51-500) | E36: Aarav | F36: Marketing Director | G36: aarav@redshift.com | H36: Trade Show/Event | I36: 14-02-2025 | J36: Karan Bhatia | K36: 3 | L36: 4 | M36: 2 | N36: 3 | O36: =SUM(K36:N36) -> 12 | P36: =IF(O36>=15,"Yes","No") -> No | Q36: New Lead | R36: 617000 | S36: 0.05 | T36: =R36*S36 -> 30850 | U36: 26-04-2025
A37: LD2036 | B37: Foxglove Ventures | C37: E-commerce | D37: Small (1-50) | E37: Vivaan | F37: Head of Operations | G37: vivaan@foxglove.com | H37: Referral | I37: 29-03-2025 | J37: Ananya Kapoor | K37: 5 | L37: 2 | M37: 1 | N37: 2 | O37: =SUM(K37:N37) -> 10 | P37: =IF(O37>=15,"Yes","No") -> No | Q37: Closed Lost | R37: 147000 | S37: 0 | T37: =R37*S37 -> 0 | U37: 22-04-2025 | V37: 25-04-2025 | W37: 27 | X37: Chose competitor
A38: LD2037 | B38: Ridge Traders | C38: E-commerce | D38: Small (1-50) | E38: Aditya | F38: COO | G38: aditya@ridge.com | H38: Inbound - Website | I38: 01-05-2026 | J38: Rohit Malhotra | K38: 4 | L38: 4 | M38: 2 | N38: 4 | O38: =SUM(K38:N38) -> 14 | P38: =IF(O38>=15,"Yes","No") -> No | Q38: Proposal Sent | R38: 227000 | S38: 0.55 | T38: =R38*S38 -> 124850 | U38: 01-07-2026
A39: LD2038 | B39: Orbit Group | C39: Manufacturing | D39: Mid-Market (51-500) | E39: Pooja | F39: IT Manager | G39: pooja@orbit.com | H39: LinkedIn Outreach | I39: 18-09-2025 | J39: Rohit Malhotra | K39: 2 | L39: 2 | M39: 1 | N39: 3 | O39: =SUM(K39:N39) -> 8 | P39: =IF(O39>=15,"Yes","No") -> No | Q39: Contacted | R39: 704000 | S39: 0.15 | T39: =R39*S39 -> 105600 | U39: 20-11-2025
A40: LD2039 | B40: Anchor Mart | C40: Retail | D40: Mid-Market (51-500) | E40: Vivaan | F40: Procurement Manager | G40: vivaan@anchor.com | H40: Cold Outbound | I40: 20-10-2025 | J40: Divya Nair | K40: 1 | L40: 2 | M40: 1 | N40: 3 | O40: =SUM(K40:N40) -> 7 | P40: =IF(O40>=15,"Yes","No") -> No | Q40: Contacted | R40: 865000 | S40: 0.15 | T40: =R40*S40 -> 129750 | U40: 10-11-2025
A41: LD2040 | B41: Havenly Industries | C41: Healthcare | D41: Enterprise (500+) | E41: Arjun | F41: Head of Operations | G41: arjun@havenly.com | H41: Cold Outbound | I41: 03-10-2025 | J41: Ananya Kapoor | K41: 1 | L41: 3 | M41: 2 | N41: 3 | O41: =SUM(K41:N41) -> 9 | P41: =IF(O41>=15,"Yes","No") -> No | Q41: Contacted | R41: 2304000 | S41: 0.15 | T41: =R41*S41 -> 345600 | U41: 08-11-2025
A42: LD2041 | B42: Anchor Industries | C42: FMCG | D42: Enterprise (500+) | E42: Zara | F42: COO | G42: zara@anchor.com | H42: Inbound - Website | I42: 09-01-2026 | J42: Ananya Kapoor | K42: 1 | L42: 4 | M42: 4 | N42: 3 | O42: =SUM(K42:N42) -> 12 | P42: =IF(O42>=15,"Yes","No") -> No | Q42: Contacted | R42: 2506000 | S42: 0.15 | T42: =R42*S42 -> 375900 | U42: 23-02-2026
A43: LD2042 | B43: Ridge Retail | C43: Retail | D43: Mid-Market (51-500) | E43: Sana | F43: IT Manager | G43: sana@ridge.com | H43: Inbound - Website | I43: 21-01-2026 | J43: Sneha Iyer | K43: 2 | L43: 5 | M43: 4 | N43: 3 | O43: =SUM(K43:N43) -> 14 | P43: =IF(O43>=15,"Yes","No") -> No | Q43: New Lead | R43: 626000 | S43: 0.05 | T43: =R43*S43 -> 31300 | U43: 17-02-2026
A44: LD2043 | B44: Solstice & Co | C44: Education | D44: Small (1-50) | E44: Dev | F44: Marketing Director | G44: dev@solstice.com | H44: Referral | I44: 17-01-2026 | J44: Ananya Kapoor | K44: 4 | L44: 5 | M44: 4 | N44: 4 | O44: =SUM(K44:N44) -> 17 | P44: =IF(O44>=15,"Yes","No") -> Yes | Q44: Closed Won | R44: 164000 | S44: 1 | T44: =R44*S44 -> 164000 | U44: 21-02-2026 | V44: 23-02-2026 | W44: 37
A45: LD2044 | B45: Summit Group | C45: Retail | D45: Small (1-50) | E45: Vivaan | F45: VP Sales | G45: vivaan@summit.com | H45: LinkedIn Outreach | I45: 18-01-2026 | J45: Karan Bhatia | K45: 2 | L45: 3 | M45: 2 | N45: 1 | O45: =SUM(K45:N45) -> 8 | P45: =IF(O45>=15,"Yes","No") -> No | Q45: New Lead | R45: 240000 | S45: 0.05 | T45: =R45*S45 -> 12000 | U45: 14-03-2026
A46: LD2045 | B46: Anchor Mart | C46: Manufacturing | D46: Mid-Market (51-500) | E46: Nikhil | F46: Head of Operations | G46: nikhil@anchor.com | H46: Cold Outbound | I46: 25-02-2026 | J46: Sneha Iyer | K46: 2 | L46: 1 | M46: 1 | N46: 2 | O46: =SUM(K46:N46) -> 6 | P46: =IF(O46>=15,"Yes","No") -> No | Q46: Closed Lost | R46: 881000 | S46: 0 | T46: =R46*S46 -> 0 | U46: 01-04-2026 | V46: 09-04-2026 | W46: 43 | X46: Chose competitor
A47: LD2046 | B47: Palm & Co | C47: FMCG | D47: Small (1-50) | E47: Aditya | F47: Marketing Director | G47: aditya@palm.com | H47: LinkedIn Outreach | I47: 21-06-2025 | J47: Karan Bhatia | K47: 4 | L47: 1 | M47: 1 | N47: 2 | O47: =SUM(K47:N47) -> 8 | P47: =IF(O47>=15,"Yes","No") -> No | Q47: Contacted | R47: 147000 | S47: 0.15 | T47: =R47*S47 -> 22050 | U47: 28-08-2025
A48: LD2047 | B48: Ironclad Solutions | C48: Retail | D48: Small (1-50) | E48: Dev | F48: VP Sales | G48: dev@ironclad.com | H48: Referral | I48: 07-09-2025 | J48: Rohit Malhotra | K48: 4 | L48: 4 | M48: 3 | N48: 4 | O48: =SUM(K48:N48) -> 15 | P48: =IF(O48>=15,"Yes","No") -> Yes | Q48: Closed Lost | R48: 160000 | S48: 0 | T48: =R48*S48 -> 0 | U48: 10-10-2025 | V48: 23-09-2025 | W48: 16 | X48: Bad timing
A49: LD2048 | B49: Ember Mart | C49: Retail | D49: Enterprise (500+) | E49: Pooja | F49: VP Sales | G49: pooja@ember.com | H49: Inbound - Website | I49: 26-05-2026 | J49: Divya Nair | K49: 3 | L49: 3 | M49: 4 | N49: 1 | O49: =SUM(K49:N49) -> 11 | P49: =IF(O49>=15,"Yes","No") -> No | Q49: Closed Lost | R49: 2925000 | S49: 0 | T49: =R49*S49 -> 0 | U49: 12-07-2026 | V49: 21-06-2026 | W49: 26 | X49: Budget too high
A50: LD2049 | B50: Orbit Group | C50: Education | D50: Enterprise (500+) | E50: Aditya | F50: Founder/CEO | G50: aditya@orbit.com | H50: Cold Outbound | I50: 16-03-2025 | J50: Karan Bhatia | K50: 2 | L50: 3 | M50: 3 | N50: 1 | O50: =SUM(K50:N50) -> 9 | P50: =IF(O50>=15,"Yes","No") -> No | Q50: New Lead | R50: 2893000 | S50: 0.05 | T50: =R50*S50 -> 144650 | U50: 20-04-2025
A51: LD2050 | B51: Cobalt & Co | C51: Manufacturing | D51: Mid-Market (51-500) | E51: Meera | F51: Head of Operations | G51: meera@cobalt.com | H51: Partner Channel | I51: 22-04-2025 | J51: Karan Bhatia | K51: 4 | L51: 4 | M51: 3 | N51: 3 | O51: =SUM(K51:N51) -> 14 | P51: =IF(O51>=15,"Yes","No") -> No | Q51: Closed Lost | R51: 693000 | S51: 0 | T51: =R51*S51 -> 0 | U51: 14-06-2025 | V51: 08-05-2025 | W51: 16 | X51: No decision / went dark
A52: LD2051 | B52: Summit Group | C52: Retail | D52: Enterprise (500+) | E52: Aarav | F52: Growth Lead | G52: aarav@summit.com | H52: Inbound - Website | I52: 14-03-2025 | J52: Sneha Iyer | K52: 4 | L52: 3 | M52: 4 | N52: 2 | O52: =SUM(K52:N52) -> 13 | P52: =IF(O52>=15,"Yes","No") -> No | Q52: Closed Lost | R52: 2185000 | S52: 0 | T52: =R52*S52 -> 0 | U52: 18-04-2025 | V52: 23-04-2025 | W52: 40 | X52: Chose competitor
A53: LD2052 | B53: Meridian Mart | C53: Healthcare | D53: Small (1-50) | E53: Ishita | F53: COO | G53: ishita@meridian.com | H53: Referral | I53: 11-11-2025 | J53: Karan Bhatia | K53: 3 | L53: 5 | M53: 3 | N53: 4 | O53: =SUM(K53:N53) -> 15 | P53: =IF(O53>=15,"Yes","No") -> Yes | Q53: Contacted | R53: 160000 | S53: 0.15 | T53: =R53*S53 -> 24000 | U53: 24-12-2025
A54: LD2053 | B54: Bluepeak Group | C54: Retail | D54: Small (1-50) | E54: Pooja | F54: Marketing Director | G54: pooja@bluepeak.com | H54: Cold Outbound | I54: 07-03-2026 | J54: Sneha Iyer | K54: 1 | L54: 2 | M54: 2 | N54: 3 | O54: =SUM(K54:N54) -> 8 | P54: =IF(O54>=15,"Yes","No") -> No | Q54: New Lead | R54: 140000 | S54: 0.05 | T54: =R54*S54 -> 7000 | U54: 28-04-2026
A55: LD2054 | B55: Orbit Mart | C55: FMCG | D55: Small (1-50) | E55: Riya | F55: Marketing Director | G55: riya@orbit.com | H55: LinkedIn Outreach | I55: 16-11-2025 | J55: Sneha Iyer | K55: 1 | L55: 3 | M55: 3 | N55: 2 | O55: =SUM(K55:N55) -> 9 | P55: =IF(O55>=15,"Yes","No") -> No | Q55: New Lead | R55: 192000 | S55: 0.05 | T55: =R55*S55 -> 9600 | U55: 24-12-2025
A56: LD2055 | B56: Ridge Retail | C56: Healthcare | D56: Mid-Market (51-500) | E56: Aditya | F56: Growth Lead | G56: aditya@ridge.com | H56: Cold Outbound | I56: 12-05-2026 | J56: Rohit Malhotra | K56: 3 | L56: 2 | M56: 1 | N56: 2 | O56: =SUM(K56:N56) -> 8 | P56: =IF(O56>=15,"Yes","No") -> No | Q56: New Lead | R56: 800000 | S56: 0.05 | T56: =R56*S56 -> 40000 | U56: 04-06-2026
A57: LD2056 | B57: Ridge Industries | C57: FMCG | D57: Small (1-50) | E57: Yash | F57: VP Sales | G57: yash@ridge.com | H57: LinkedIn Outreach | I57: 23-02-2025 | J57: Sneha Iyer | K57: 2 | L57: 2 | M57: 3 | N57: 3 | O57: =SUM(K57:N57) -> 10 | P57: =IF(O57>=15,"Yes","No") -> No | Q57: Contacted | R57: 148000 | S57: 0.15 | T57: =R57*S57 -> 22200 | U57: 05-04-2025
A58: LD2057 | B58: Anchor & Co | C58: E-commerce | D58: Small (1-50) | E58: Vivaan | F58: VP Sales | G58: vivaan@anchor.com | H58: LinkedIn Outreach | I58: 16-11-2025 | J58: Sneha Iyer | K58: 2 | L58: 3 | M58: 2 | N58: 4 | O58: =SUM(K58:N58) -> 11 | P58: =IF(O58>=15,"Yes","No") -> No | Q58: Closed Lost | R58: 154000 | S58: 0 | T58: =R58*S58 -> 0 | U58: 24-01-2026 | V58: 11-12-2025 | W58: 25 | X58: No decision / went dark
A59: LD2058 | B59: Ridge Traders | C59: FMCG | D59: Mid-Market (51-500) | E59: Dev | F59: COO | G59: dev@ridge.com | H59: Inbound - Website | I59: 30-04-2026 | J59: Sneha Iyer | K59: 4 | L59: 4 | M59: 2 | N59: 2 | O59: =SUM(K59:N59) -> 12 | P59: =IF(O59>=15,"Yes","No") -> No | Q59: Closed Won | R59: 550000 | S59: 1 | T59: =R59*S59 -> 550000 | U59: 05-06-2026 | V59: 26-05-2026 | W59: 26
A60: LD2059 | B60: Nova Traders | C60: Retail | D60: Enterprise (500+) | E60: Aarav | F60: Marketing Director | G60: aarav@nova.com | H60: Inbound - Website | I60: 06-10-2025 | J60: Sneha Iyer | K60: 1 | L60: 4 | M60: 2 | N60: 1 | O60: =SUM(K60:N60) -> 8 | P60: =IF(O60>=15,"Yes","No") -> No | Q60: New Lead | R60: 2043000 | S60: 0.05 | T60: =R60*S60 -> 102150 | U60: 14-11-2025
A61: LD2060 | B61: Quartz Industries | C61: Hospitality | D61: Enterprise (500+) | E61: Pooja | F61: Founder/CEO | G61: pooja@quartz.com | H61: Cold Outbound | I61: 20-04-2025 | J61: Karan Bhatia | K61: 1 | L61: 1 | M61: 1 | N61: 1 | O61: =SUM(K61:N61) -> 4 | P61: =IF(O61>=15,"Yes","No") -> No | Q61: New Lead | R61: 2978000 | S61: 0.05 | T61: =R61*S61 -> 148900 | U61: 06-06-2025
A62: LD2061 | B62: Havenly Traders | C62: Education | D62: Mid-Market (51-500) | E62: Kabir | F62: Growth Lead | G62: kabir@havenly.com | H62: Trade Show/Event | I62: 09-01-2025 | J62: Rohit Malhotra | K62: 3 | L62: 2 | M62: 1 | N62: 4 | O62: =SUM(K62:N62) -> 10 | P62: =IF(O62>=15,"Yes","No") -> No | Q62: Contacted | R62: 686000 | S62: 0.15 | T62: =R62*S62 -> 102900 | U62: 27-02-2025
A63: LD2062 | B63: Bluepeak Solutions | C63: Retail | D63: Small (1-50) | E63: Vivaan | F63: Marketing Director | G63: vivaan@bluepeak.com | H63: Inbound - Website | I63: 13-06-2025 | J63: Divya Nair | K63: 3 | L63: 3 | M63: 4 | N63: 4 | O63: =SUM(K63:N63) -> 14 | P63: =IF(O63>=15,"Yes","No") -> No | Q63: Contacted | R63: 177000 | S63: 0.15 | T63: =R63*S63 -> 26550 | U63: 09-07-2025
A64: LD2063 | B64: Granite Solutions | C64: Hospitality | D64: Enterprise (500+) | E64: Sana | F64: IT Manager | G64: sana@granite.com | H64: Cold Outbound | I64: 09-04-2025 | J64: Rohit Malhotra | K64: 4 | L64: 2 | M64: 3 | N64: 1 | O64: =SUM(K64:N64) -> 10 | P64: =IF(O64>=15,"Yes","No") -> No | Q64: Proposal Sent | R64: 2043000 | S64: 0.55 | T64: =R64*S64 -> 1123650 | U64: 06-05-2025
A65: LD2064 | B65: Cobalt Mart | C65: Retail | D65: Mid-Market (51-500) | E65: Ishita | F65: Head of Operations | G65: ishita@cobalt.com | H65: Cold Outbound | I65: 02-10-2025 | J65: Rohit Malhotra | K65: 2 | L65: 2 | M65: 1 | N65: 1 | O65: =SUM(K65:N65) -> 6 | P65: =IF(O65>=15,"Yes","No") -> No | Q65: Closed Lost | R65: 866000 | S65: 0 | T65: =R65*S65 -> 0 | U65: 28-10-2025 | V65: 31-10-2025 | W65: 29 | X65: No decision / went dark
A66: LD2065 | B66: Willow Solutions | C66: Education | D66: Mid-Market (51-500) | E66: Aarav | F66: Head of Operations | G66: aarav@willow.com | H66: Cold Outbound | I66: 05-01-2025 | J66: Sneha Iyer | K66: 1 | L66: 3 | M66: 1 | N66: 1 | O66: =SUM(K66:N66) -> 6 | P66: =IF(O66>=15,"Yes","No") -> No | Q66: Closed Won | R66: 902000 | S66: 1 | T66: =R66*S66 -> 902000 | U66: 22-02-2025 | V66: 04-02-2025 | W66: 30
A67: LD2066 | B67: Willow Group | C67: Retail | D67: Small (1-50) | E67: Aarav | F67: COO | G67: aarav@willow.com | H67: Inbound - Website | I67: 25-12-2025 | J67: Rohit Malhotra | K67: 3 | L67: 4 | M67: 4 | N67: 1 | O67: =SUM(K67:N67) -> 12 | P67: =IF(O67>=15,"Yes","No") -> No | Q67: New Lead | R67: 229000 | S67: 0.05 | T67: =R67*S67 -> 11450 | U67: 16-01-2026
A68: LD2067 | B68: Lumen Traders | C68: E-commerce | D68: Small (1-50) | E68: Nikhil | F68: Founder/CEO | G68: nikhil@lumen.com | H68: LinkedIn Outreach | I68: 23-02-2026 | J68: Rohit Malhotra | K68: 1 | L68: 1 | M68: 5 | N68: 1 | O68: =SUM(K68:N68) -> 8 | P68: =IF(O68>=15,"Yes","No") -> No | Q68: Contacted | R68: 212000 | S68: 0.15 | T68: =R68*S68 -> 31800 | U68: 19-03-2026
A69: LD2068 | B69: Foxglove Enterprises | C69: E-commerce | D69: Small (1-50) | E69: Zara | F69: Growth Lead | G69: zara@foxglove.com | H69: LinkedIn Outreach | I69: 04-04-2025 | J69: Sneha Iyer | K69: 2 | L69: 1 | M69: 2 | N69: 3 | O69: =SUM(K69:N69) -> 8 | P69: =IF(O69>=15,"Yes","No") -> No | Q69: Contacted | R69: 173000 | S69: 0.15 | T69: =R69*S69 -> 25950 | U69: 13-05-2025
A70: LD2069 | B70: Granite Industries | C70: E-commerce | D70: Enterprise (500+) | E70: Aditya | F70: VP Sales | G70: aditya@granite.com | H70: Trade Show/Event | I70: 19-01-2025 | J70: Rohit Malhotra | K70: 3 | L70: 3 | M70: 1 | N70: 4 | O70: =SUM(K70:N70) -> 11 | P70: =IF(O70>=15,"Yes","No") -> No | Q70: Closed Won | R70: 2185000 | S70: 1 | T70: =R70*S70 -> 2185000 | U70: 09-03-2025 | V70: 18-02-2025 | W70: 30
A71: LD2070 | B71: Zenith Enterprises | C71: Healthcare | D71: Mid-Market (51-500) | E71: Sana | F71: Founder/CEO | G71: sana@zenith.com | H71: Cold Outbound | I71: 22-02-2025 | J71: Ananya Kapoor | K71: 1 | L71: 1 | M71: 1 | N71: 1 | O71: =SUM(K71:N71) -> 4 | P71: =IF(O71>=15,"Yes","No") -> No | Q71: Contacted | R71: 726000 | S71: 0.15 | T71: =R71*S71 -> 108900 | U71: 24-03-2025
A72: LD2071 | B72: Crestline Retail | C72: FMCG | D72: Small (1-50) | E72: Nikhil | F72: Head of Operations | G72: nikhil@crestline.com | H72: Partner Channel | I72: 25-06-2025 | J72: Rohit Malhotra | K72: 4 | L72: 2 | M72: 3 | N72: 3 | O72: =SUM(K72:N72) -> 12 | P72: =IF(O72>=15,"Yes","No") -> No | Q72: Contacted | R72: 183000 | S72: 0.15 | T72: =R72*S72 -> 27450 | U72: 14-08-2025
A73: LD2072 | B73: Quartz Industries | C73: Manufacturing | D73: Enterprise (500+) | E73: Kabir | F73: VP Sales | G73: kabir@quartz.com | H73: LinkedIn Outreach | I73: 14-06-2025 | J73: Divya Nair | K73: 1 | L73: 4 | M73: 1 | N73: 1 | O73: =SUM(K73:N73) -> 7 | P73: =IF(O73>=15,"Yes","No") -> No | Q73: New Lead | R73: 1942000 | S73: 0.05 | T73: =R73*S73 -> 97100 | U73: 26-08-2025
A74: LD2073 | B74: Crestline Traders | C74: E-commerce | D74: Small (1-50) | E74: Nikhil | F74: Procurement Manager | G74: nikhil@crestline.com | H74: Partner Channel | I74: 14-02-2026 | J74: Rohit Malhotra | K74: 4 | L74: 4 | M74: 5 | N74: 3 | O74: =SUM(K74:N74) -> 16 | P74: =IF(O74>=15,"Yes","No") -> Yes | Q74: Qualified | R74: 196000 | S74: 0.35 | T74: =R74*S74 -> 68600 | U74: 17-04-2026
A75: LD2074 | B75: Nova Retail | C75: E-commerce | D75: Small (1-50) | E75: Pooja | F75: Procurement Manager | G75: pooja@nova.com | H75: LinkedIn Outreach | I75: 10-11-2025 | J75: Karan Bhatia | K75: 1 | L75: 3 | M75: 2 | N75: 2 | O75: =SUM(K75:N75) -> 8 | P75: =IF(O75>=15,"Yes","No") -> No | Q75: Contacted | R75: 227000 | S75: 0.15 | T75: =R75*S75 -> 34050 | U75: 11-12-2025
A76: LD2075 | B76: Orbit Traders | C76: Education | D76: Mid-Market (51-500) | E76: Aditya | F76: COO | G76: aditya@orbit.com | H76: Cold Outbound | I76: 29-08-2025 | J76: Rohit Malhotra | K76: 1 | L76: 2 | M76: 1 | N76: 2 | O76: =SUM(K76:N76) -> 6 | P76: =IF(O76>=15,"Yes","No") -> No | Q76: New Lead | R76: 525000 | S76: 0.05 | T76: =R76*S76 -> 26250 | U76: 13-10-2025
A77: LD2076 | B77: Willow Traders | C77: FMCG | D77: Mid-Market (51-500) | E77: Kabir | F77: Founder/CEO | G77: kabir@willow.com | H77: Cold Outbound | I77: 17-03-2026 | J77: Ananya Kapoor | K77: 1 | L77: 1 | M77: 2 | N77: 1 | O77: =SUM(K77:N77) -> 5 | P77: =IF(O77>=15,"Yes","No") -> No | Q77: Closed Lost | R77: 777000 | S77: 0 | T77: =R77*S77 -> 0 | U77: 10-04-2026 | V77: 25-04-2026 | W77: 39 | X77: Budget too high
A78: LD2077 | B78: Northstar Enterprises | C78: Education | D78: Mid-Market (51-500) | E78: Arjun | F78: Procurement Manager | G78: arjun@northstar.com | H78: Inbound - Website | I78: 19-05-2026 | J78: Rohit Malhotra | K78: 2 | L78: 3 | M78: 2 | N78: 2 | O78: =SUM(K78:N78) -> 9 | P78: =IF(O78>=15,"Yes","No") -> No | Q78: Contacted | R78: 893000 | S78: 0.15 | T78: =R78*S78 -> 133950 | U78: 24-06-2026
A79: LD2078 | B79: Solstice Traders | C79: FMCG | D79: Enterprise (500+) | E79: Ishita | F79: COO | G79: ishita@solstice.com | H79: Inbound - Website | I79: 28-05-2025 | J79: Divya Nair | K79: 1 | L79: 4 | M79: 1 | N79: 3 | O79: =SUM(K79:N79) -> 9 | P79: =IF(O79>=15,"Yes","No") -> No | Q79: Closed Lost | R79: 2485000 | S79: 0 | T79: =R79*S79 -> 0 | U79: 27-06-2025 | V79: 08-07-2025 | W79: 41 | X79: Feature gap
A80: LD2079 | B80: Foxglove Enterprises | C80: Healthcare | D80: Mid-Market (51-500) | E80: Arjun | F80: Growth Lead | G80: arjun@foxglove.com | H80: Cold Outbound | I80: 09-04-2026 | J80: Ananya Kapoor | K80: 2 | L80: 3 | M80: 1 | N80: 1 | O80: =SUM(K80:N80) -> 7 | P80: =IF(O80>=15,"Yes","No") -> No | Q80: Contacted | R80: 754000 | S80: 0.15 | T80: =R80*S80 -> 113100 | U80: 24-05-2026
A81: LD2080 | B81: Anchor Ventures | C81: Logistics | D81: Small (1-50) | E81: Arjun | F81: IT Manager | G81: arjun@anchor.com | H81: Cold Outbound | I81: 13-01-2026 | J81: Karan Bhatia | K81: 2 | L81: 1 | M81: 1 | N81: 1 | O81: =SUM(K81:N81) -> 5 | P81: =IF(O81>=15,"Yes","No") -> No | Q81: Contacted | R81: 241000 | S81: 0.15 | T81: =R81*S81 -> 36150 | U81: 05-02-2026
A82: LD2081 | B82: Vertex Industries | C82: Retail | D82: Mid-Market (51-500) | E82: Pooja | F82: Marketing Director | G82: pooja@vertex.com | H82: LinkedIn Outreach | I82: 17-11-2025 | J82: Sneha Iyer | K82: 2 | L82: 1 | M82: 1 | N82: 1 | O82: =SUM(K82:N82) -> 5 | P82: =IF(O82>=15,"Yes","No") -> No | Q82: Contacted | R82: 504000 | S82: 0.15 | T82: =R82*S82 -> 75600 | U82: 30-12-2025
A83: LD2082 | B83: Meridian Industries | C83: E-commerce | D83: Small (1-50) | E83: Yash | F83: Head of Operations | G83: yash@meridian.com | H83: Referral | I83: 16-02-2025 | J83: Ananya Kapoor | K83: 3 | L83: 2 | M83: 5 | N83: 4 | O83: =SUM(K83:N83) -> 14 | P83: =IF(O83>=15,"Yes","No") -> No | Q83: Closed Lost | R83: 236000 | S83: 0 | T83: =R83*S83 -> 0 | U83: 28-04-2025 | V83: 25-03-2025 | W83: 37 | X83: Budget too high
A84: LD2083 | B84: Vertex Ventures | C84: Education | D84: Enterprise (500+) | E84: Kavya | F84: Procurement Manager | G84: kavya@vertex.com | H84: Cold Outbound | I84: 07-03-2025 | J84: Karan Bhatia | K84: 1 | L84: 1 | M84: 1 | N84: 3 | O84: =SUM(K84:N84) -> 6 | P84: =IF(O84>=15,"Yes","No") -> No | Q84: New Lead | R84: 1664000 | S84: 0.05 | T84: =R84*S84 -> 83200 | U84: 27-03-2025
A85: LD2084 | B85: Zenith & Co | C85: Retail | D85: Enterprise (500+) | E85: Kabir | F85: Growth Lead | G85: kabir@zenith.com | H85: Inbound - Website | I85: 20-05-2026 | J85: Divya Nair | K85: 5 | L85: 4 | M85: 4 | N85: 3 | O85: =SUM(K85:N85) -> 16 | P85: =IF(O85>=15,"Yes","No") -> Yes | Q85: Closed Lost | R85: 2319000 | S85: 0 | T85: =R85*S85 -> 0 | U85: 21-06-2026 | V85: 05-06-2026 | W85: 16 | X85: No decision / went dark
A86: LD2085 | B86: Ironclad & Co | C86: Manufacturing | D86: Small (1-50) | E86: Yash | F86: Head of Operations | G86: yash@ironclad.com | H86: Cold Outbound | I86: 28-06-2025 | J86: Karan Bhatia | K86: 1 | L86: 2 | M86: 2 | N86: 1 | O86: =SUM(K86:N86) -> 6 | P86: =IF(O86>=15,"Yes","No") -> No | Q86: New Lead | R86: 162000 | S86: 0.05 | T86: =R86*S86 -> 8100 | U86: 18-07-2025
A87: LD2086 | B87: Cobalt Ventures | C87: E-commerce | D87: Enterprise (500+) | E87: Zara | F87: IT Manager | G87: zara@cobalt.com | H87: Inbound - Website | I87: 09-04-2026 | J87: Ananya Kapoor | K87: 3 | L87: 3 | M87: 2 | N87: 4 | O87: =SUM(K87:N87) -> 12 | P87: =IF(O87>=15,"Yes","No") -> No | Q87: Contacted | R87: 2884000 | S87: 0.15 | T87: =R87*S87 -> 432600 | U87: 16-05-2026
A88: LD2087 | B88: Foxglove Group | C88: Retail | D88: Enterprise (500+) | E88: Riya | F88: COO | G88: riya@foxglove.com | H88: LinkedIn Outreach | I88: 30-10-2025 | J88: Divya Nair | K88: 3 | L88: 4 | M88: 1 | N88: 1 | O88: =SUM(K88:N88) -> 9 | P88: =IF(O88>=15,"Yes","No") -> No | Q88: Contacted | R88: 2953000 | S88: 0.15 | T88: =R88*S88 -> 442950 | U88: 11-01-2026
A89: LD2088 | B89: Nova & Co | C89: Retail | D89: Small (1-50) | E89: Tanya | F89: IT Manager | G89: tanya@nova.com | H89: Trade Show/Event | I89: 16-07-2025 | J89: Divya Nair | K89: 2 | L89: 3 | M89: 3 | N89: 2 | O89: =SUM(K89:N89) -> 10 | P89: =IF(O89>=15,"Yes","No") -> No | Q89: Contacted | R89: 195000 | S89: 0.15 | T89: =R89*S89 -> 29250 | U89: 28-09-2025
A90: LD2089 | B90: Vertex Industries | C90: FMCG | D90: Mid-Market (51-500) | E90: Ishita | F90: Head of Operations | G90: ishita@vertex.com | H90: Cold Outbound | I90: 06-08-2025 | J90: Rohit Malhotra | K90: 1 | L90: 1 | M90: 2 | N90: 1 | O90: =SUM(K90:N90) -> 5 | P90: =IF(O90>=15,"Yes","No") -> No | Q90: Closed Lost | R90: 653000 | S90: 0 | T90: =R90*S90 -> 0 | U90: 27-08-2025 | V90: 18-08-2025 | W90: 12 | X90: Bad timing
A91: LD2090 | B91: Granite & Co | C91: E-commerce | D91: Mid-Market (51-500) | E91: Meera | F91: Marketing Director | G91: meera@granite.com | H91: Referral | I91: 17-02-2025 | J91: Divya Nair | K91: 4 | L91: 3 | M91: 3 | N91: 3 | O91: =SUM(K91:N91) -> 13 | P91: =IF(O91>=15,"Yes","No") -> No | Q91: New Lead | R91: 540000 | S91: 0.05 | T91: =R91*S91 -> 27000 | U91: 13-03-2025
A92: LD2091 | B92: Cobalt Solutions | C92: Healthcare | D92: Small (1-50) | E92: Pooja | F92: Head of Operations | G92: pooja@cobalt.com | H92: Inbound - Website | I92: 30-07-2025 | J92: Ananya Kapoor | K92: 2 | L92: 4 | M92: 3 | N92: 4 | O92: =SUM(K92:N92) -> 13 | P92: =IF(O92>=15,"Yes","No") -> No | Q92: New Lead | R92: 153000 | S92: 0.05 | T92: =R92*S92 -> 7650 | U92: 28-09-2025
A93: LD2092 | B93: Granite Ventures | C93: Retail | D93: Mid-Market (51-500) | E93: Pooja | F93: IT Manager | G93: pooja@granite.com | H93: Referral | I93: 16-05-2025 | J93: Sneha Iyer | K93: 5 | L93: 5 | M93: 4 | N93: 4 | O93: =SUM(K93:N93) -> 18 | P93: =IF(O93>=15,"Yes","No") -> Yes | Q93: Closed Lost | R93: 616000 | S93: 0 | T93: =R93*S93 -> 0 | U93: 25-06-2025 | V93: 07-06-2025 | W93: 22 | X93: No decision / went dark
A94: LD2093 | B94: Anchor Industries | C94: FMCG | D94: Small (1-50) | E94: Zara | F94: VP Sales | G94: zara@anchor.com | H94: LinkedIn Outreach | I94: 01-02-2025 | J94: Ananya Kapoor | K94: 5 | L94: 1 | M94: 3 | N94: 2 | O94: =SUM(K94:N94) -> 11 | P94: =IF(O94>=15,"Yes","No") -> No | Q94: Qualified | R94: 217000 | S94: 0.35 | T94: =R94*S94 -> 75950 | U94: 29-03-2025
A95: LD2094 | B95: Northstar Mart | C95: Retail | D95: Mid-Market (51-500) | E95: Kavya | F95: IT Manager | G95: kavya@northstar.com | H95: Inbound - Website | I95: 26-07-2025 | J95: Sneha Iyer | K95: 3 | L95: 4 | M95: 1 | N95: 3 | O95: =SUM(K95:N95) -> 11 | P95: =IF(O95>=15,"Yes","No") -> No | Q95: Contacted | R95: 620000 | S95: 0.15 | T95: =R95*S95 -> 93000 | U95: 06-10-2025
A96: LD2095 | B96: Ironclad Traders | C96: Logistics | D96: Small (1-50) | E96: Zara | F96: VP Sales | G96: zara@ironclad.com | H96: Inbound - Website | I96: 12-06-2025 | J96: Karan Bhatia | K96: 3 | L96: 2 | M96: 2 | N96: 4 | O96: =SUM(K96:N96) -> 11 | P96: =IF(O96>=15,"Yes","No") -> No | Q96: Closed Lost | R96: 191000 | S96: 0 | T96: =R96*S96 -> 0 | U96: 27-07-2025 | V96: 28-06-2025 | W96: 16 | X96: No decision / went dark
A97: LD2096 | B97: Summit Retail | C97: Healthcare | D97: Small (1-50) | E97: Kavya | F97: COO | G97: kavya@summit.com | H97: Inbound - Website | I97: 16-01-2026 | J97: Divya Nair | K97: 4 | L97: 3 | M97: 1 | N97: 3 | O97: =SUM(K97:N97) -> 11 | P97: =IF(O97>=15,"Yes","No") -> No | Q97: Contacted | R97: 169000 | S97: 0.15 | T97: =R97*S97 -> 25350 | U97: 13-02-2026
A98: LD2097 | B98: Tidal Group | C98: FMCG | D98: Mid-Market (51-500) | E98: Aditya | F98: COO | G98: aditya@tidal.com | H98: Trade Show/Event | I98: 09-06-2025 | J98: Sneha Iyer | K98: 4 | L98: 4 | M98: 3 | N98: 2 | O98: =SUM(K98:N98) -> 13 | P98: =IF(O98>=15,"Yes","No") -> No | Q98: Contacted | R98: 825000 | S98: 0.15 | T98: =R98*S98 -> 123750 | U98: 15-07-2025
A99: LD2098 | B99: Redshift Enterprises | C99: FMCG | D99: Mid-Market (51-500) | E99: Riya | F99: Marketing Director | G99: riya@redshift.com | H99: LinkedIn Outreach | I99: 19-04-2026 | J99: Sneha Iyer | K99: 3 | L99: 4 | M99: 2 | N99: 3 | O99: =SUM(K99:N99) -> 12 | P99: =IF(O99>=15,"Yes","No") -> No | Q99: Qualified | R99: 517000 | S99: 0.35 | T99: =R99*S99 -> 180950 | U99: 16-06-2026
A100: LD2099 | B100: Anchor & Co | C100: Hospitality | D100: Small (1-50) | E100: Arjun | F100: Marketing Director | G100: arjun@anchor.com | H100: Partner Channel | I100: 02-12-2025 | J100: Ananya Kapoor | K100: 2 | L100: 4 | M100: 5 | N100: 2 | O100: =SUM(K100:N100) -> 13 | P100: =IF(O100>=15,"Yes","No") -> No | Q100: Qualified | R100: 153000 | S100: 0.35 | T100: =R100*S100 -> 53550 | U100: 06-02-2026
...

Sheet Funnel Summary
B2: B2B Sales Pipeline — Funnel Summary
B4: Stage | C4: Leads | D4: Stage Value (INR) | E4: Weighted Value (INR) | F4: % of Total Leads | G4: Conversion from Prev Stage %
B5: New Lead | C5: =COUNTIFS(Pipeline!$Q$2:$Q$601,B5) -> 160 | D5: =SUMIFS(Pipeline!$R$2:$R$601,Pipeline!$Q$2:$Q$601,B5) -> 127861000 | E5: =SUMIFS(Pipeline!$T$2:$T$601,Pipeline!$Q$2:$Q$601,B5) -> 6393050 | F5: =C5/COUNTA(Pipeline!$A$2:$A$601) -> 0.26666667 | G5: —
B6: Contacted | C6: =COUNTIFS(Pipeline!$Q$2:$Q$601,B6) -> 203 | D6: =SUMIFS(Pipeline!$R$2:$R$601,Pipeline!$Q$2:$Q$601,B6) -> 140891000 | E6: =SUMIFS(Pipeline!$T$2:$T$601,Pipeline!$Q$2:$Q$601,B6) -> 21133650 | F6: =C6/COUNTA(Pipeline!$A$2:$A$601) -> 0.33833333 | G6: =IFERROR(C6/C5,"—") -> 1.26875
B7: Qualified | C7: =COUNTIFS(Pipeline!$Q$2:$Q$601,B7) -> 54 | D7: =SUMIFS(Pipeline!$R$2:$R$601,Pipeline!$Q$2:$Q$601,B7) -> 35682000 | E7: =SUMIFS(Pipeline!$T$2:$T$601,Pipeline!$Q$2:$Q$601,B7) -> 12488700 | F7: =C7/COUNTA(Pipeline!$A$2:$A$601) -> 0.09 | G7: =IFERROR(C7/C6,"—") -> 0.26600985
B8: Proposal Sent | C8: =COUNTIFS(Pipeline!$Q$2:$Q$601,B8) -> 29 | D8: =SUMIFS(Pipeline!$R$2:$R$601,Pipeline!$Q$2:$Q$601,B8) -> 26399000 | E8: =SUMIFS(Pipeline!$T$2:$T$601,Pipeline!$Q$2:$Q$601,B8) -> 14519450 | F8: =C8/COUNTA(Pipeline!$A$2:$A$601) -> 0.048333333 | G8: =IFERROR(C8/C7,"—") -> 0.53703704
B9: Negotiation | C9: =COUNTIFS(Pipeline!$Q$2:$Q$601,B9) -> 0 | D9: =SUMIFS(Pipeline!$R$2:$R$601,Pipeline!$Q$2:$Q$601,B9) -> 0 | E9: =SUMIFS(Pipeline!$T$2:$T$601,Pipeline!$Q$2:$Q$601,B9) -> 0 | F9: =C9/COUNTA(Pipeline!$A$2:$A$601) -> 0 | G9: =IFERROR(C9/C8,"—") -> 0
B10: Closed Won | C10: =COUNTIFS(Pipeline!$Q$2:$Q$601,B10) -> 40 | D10: =SUMIFS(Pipeline!$R$2:$R$601,Pipeline!$Q$2:$Q$601,B10) -> 27963000 | E10: =SUMIFS(Pipeline!$T$2:$T$601,Pipeline!$Q$2:$Q$601,B10) -> 27963000 | F10: =C10/COUNTA(Pipeline!$A$2:$A$601) -> 0.066666667 | G10: =IFERROR(C10/C9,"—") -> —
B11: Closed Lost | C11: =COUNTIFS(Pipeline!$Q$2:$Q$601,B11) -> 114 | D11: =SUMIFS(Pipeline!$R$2:$R$601,Pipeline!$Q$2:$Q$601,B11) -> 82753000 | E11: =SUMIFS(Pipeline!$T$2:$T$601,Pipeline!$Q$2:$Q$601,B11) -> 0 | F11: =C11/COUNTA(Pipeline!$A$2:$A$601) -> 0.19 | G11: =IFERROR(C11/C10,"—") -> 2.85
B14: Overall Win Rate (Closed Won / Closed Won+Lost) | D14: =COUNTIFS(Pipeline!$Q$2:$Q$601,"Closed Won")/(COUNTIFS(Pipeline!$Q$2:$Q$601,"Closed Won")+COUNTIFS(Pipeline!$Q$2:$Q$601,"Closed Lost")) -> 0.25974026
B15: Total Open Pipeline Value (INR) | D15: =SUMIFS(Pipeline!$R$2:$R$601,Pipeline!$Q$2:$Q$601,"<>Closed Won",Pipeline!$Q$2:$Q$601,"<>Closed Lost") -> 330833000
B16: Weighted Open Pipeline Value (INR) | D16: =SUMIFS(Pipeline!$T$2:$T$601,Pipeline!$Q$2:$Q$601,"<>Closed Won",Pipeline!$Q$2:$Q$601,"<>Closed Lost") -> 54534850
B17: Closed Won Revenue (INR) | D17: =SUMIFS(Pipeline!$R$2:$R$601,Pipeline!$Q$2:$Q$601,"Closed Won") -> 27963000
B18: Average Deal Size — Closed Won (INR) | D18: =AVERAGEIFS(Pipeline!$R$2:$R$601,Pipeline!$Q$2:$Q$601,"Closed Won") -> 699075

Sheet Lead Source Analysis
A1: Lead Source | B1: Total Leads | C1: Deals Won | D1: Win Rate % | E1: Revenue Won (INR)
A2: Cold Outbound | B2: =COUNTIFS(Pipeline!$H$2:$H$601,A2) -> 173 | C2: =COUNTIFS(Pipeline!$H$2:$H$601,A2,Pipeline!$Q$2:$Q$601,"Closed Won") -> 4 | D2: =IFERROR(C2/B2,0) -> 0.023121387 | E2: =SUMIFS(Pipeline!$R$2:$R$601,Pipeline!$H$2:$H$601,A2,Pipeline!$Q$2:$Q$601,"Closed Won") -> 2538000
A3: Inbound - Website | B3: =COUNTIFS(Pipeline!$H$2:$H$601,A3) -> 132 | C3: =COUNTIFS(Pipeline!$H$2:$H$601,A3,Pipeline!$Q$2:$Q$601,"Closed Won") -> 13 | D3: =IFERROR(C3/B3,0) -> 0.098484848 | E3: =SUMIFS(Pipeline!$R$2:$R$601,Pipeline!$H$2:$H$601,A3,Pipeline!$Q$2:$Q$601,"Closed Won") -> 5936000
A4: LinkedIn Outreach | B4: =COUNTIFS(Pipeline!$H$2:$H$601,A4) -> 103 | C4: =COUNTIFS(Pipeline!$H$2:$H$601,A4,Pipeline!$Q$2:$Q$601,"Closed Won") -> 2 | D4: =IFERROR(C4/B4,0) -> 0.019417476 | E4: =SUMIFS(Pipeline!$R$2:$R$601,Pipeline!$H$2:$H$601,A4,Pipeline!$Q$2:$Q$601,"Closed Won") -> 1000000
A5: Partner Channel | B5: =COUNTIFS(Pipeline!$H$2:$H$601,A5) -> 54 | C5: =COUNTIFS(Pipeline!$H$2:$H$601,A5,Pipeline!$Q$2:$Q$601,"Closed Won") -> 5 | D5: =IFERROR(C5/B5,0) -> 0.092592593 | E5: =SUMIFS(Pipeline!$R$2:$R$601,Pipeline!$H$2:$H$601,A5,Pipeline!$Q$2:$Q$601,"Closed Won") -> 2165000
A6: Referral | B6: =COUNTIFS(Pipeline!$H$2:$H$601,A6) -> 84 | C6: =COUNTIFS(Pipeline!$H$2:$H$601,A6,Pipeline!$Q$2:$Q$601,"Closed Won") -> 12 | D6: =IFERROR(C6/B6,0) -> 0.14285714 | E6: =SUMIFS(Pipeline!$R$2:$R$601,Pipeline!$H$2:$H$601,A6,Pipeline!$Q$2:$Q$601,"Closed Won") -> 9646000
A7: Trade Show/Event | B7: =COUNTIFS(Pipeline!$H$2:$H$601,A7) -> 54 | C7: =COUNTIFS(Pipeline!$H$2:$H$601,A7,Pipeline!$Q$2:$Q$601,"Closed Won") -> 4 | D7: =IFERROR(C7/B7,0) -> 0.074074074 | E7: =SUMIFS(Pipeline!$R$2:$R$601,Pipeline!$H$2:$H$601,A7,Pipeline!$Q$2:$Q$601,"Closed Won") -> 6678000

Sheet Sales Rep Leaderboard
A1: Sales Rep | B1: Leads Owned | C1: Deals Won | D1: Win Rate % | E1: Revenue Closed (INR)
A2: Ananya Kapoor | B2: =COUNTIFS(Pipeline!$J$2:$J$601,A2) -> 114 | C2: =COUNTIFS(Pipeline!$J$2:$J$601,A2,Pipeline!$Q$2:$Q$601,"Closed Won") -> 13 | D2: =IFERROR(C2/B2,0) -> 0.11403509 | E2: =SUMIFS(Pipeline!$R$2:$R$601,Pipeline!$J$2:$J$601,A2,Pipeline!$Q$2:$Q$601,"Closed Won") -> 9182000
A3: Divya Nair | B3: =COUNTIFS(Pipeline!$J$2:$J$601,A3) -> 120 | C3: =COUNTIFS(Pipeline!$J$2:$J$601,A3,Pipeline!$Q$2:$Q$601,"Closed Won") -> 7 | D3: =IFERROR(C3/B3,0) -> 0.058333333 | E3: =SUMIFS(Pipeline!$R$2:$R$601,Pipeline!$J$2:$J$601,A3,Pipeline!$Q$2:$Q$601,"Closed Won") -> 5963000
A4: Karan Bhatia | B4: =COUNTIFS(Pipeline!$J$2:$J$601,A4) -> 117 | C4: =COUNTIFS(Pipeline!$J$2:$J$601,A4,Pipeline!$Q$2:$Q$601,"Closed Won") -> 2 | D4: =IFERROR(C4/B4,0) -> 0.017094017 | E4: =SUMIFS(Pipeline!$R$2:$R$601,Pipeline!$J$2:$J$601,A4,Pipeline!$Q$2:$Q$601,"Closed Won") -> 2947000
A5: Rohit Malhotra | B5: =COUNTIFS(Pipeline!$J$2:$J$601,A5) -> 125 | C5: =COUNTIFS(Pipeline!$J$2:$J$601,A5,Pipeline!$Q$2:$Q$601,"Closed Won") -> 3 | D5: =IFERROR(C5/B5,0) -> 0.024 | E5: =SUMIFS(Pipeline!$R$2:$R$601,Pipeline!$J$2:$J$601,A5,Pipeline!$Q$2:$Q$601,"Closed Won") -> 2559000
A6: Sneha Iyer | B6: =COUNTIFS(Pipeline!$J$2:$J$601,A6) -> 124 | C6: =COUNTIFS(Pipeline!$J$2:$J$601,A6,Pipeline!$Q$2:$Q$601,"Closed Won") -> 15 | D6: =IFERROR(C6/B6,0) -> 0.12096774 | E6: =SUMIFS(Pipeline!$R$2:$R$601,Pipeline!$J$2:$J$601,A6,Pipeline!$Q$2:$Q$601,"Closed Won") -> 7312000

Sheet BANT Matrix
B2: BANT Qualification Scoring Rubric
B4: Score | C4: Budget | D4: Authority | E4: Need | F4: Timeline
B5: 1 | C5: No budget allocated | D5: Individual contributor | E5: Vague interest | F5: No timeline
B6: 3 | C6: Budget exists, needs approval | D6: Influences decision | E6: Acknowledged problem | F6: Buying in 2 quarters
B7: 5 | C7: Budget confirmed & approved | D7: Final decision-maker | E7: Clear quantified pain point | F7: Buying in 30-60 days
B10: Win Rate by BANT Score Band (live from Pipeline data)
B11: BANT Band | C11: Leads | D11: Deals Won | E11: Win Rate %
B12: 0-10 (Poor fit) | C12: =COUNTIFS(Pipeline!$O$2:$O$601,">="&0,Pipeline!$O$2:$O$601,"<="&10) -> 308 | D12: =COUNTIFS(Pipeline!$O$2:$O$601,">="&0,Pipeline!$O$2:$O$601,"<="&10,Pipeline!$Q$2:$Q$601,"Closed Won") -> 8 | E12: =IFERROR(D12/C12,0) -> 0.025974026
B13: 11-14 (Weak fit) | C13: =COUNTIFS(Pipeline!$O$2:$O$601,">="&11,Pipeline!$O$2:$O$601,"<="&14) -> 204 | D13: =COUNTIFS(Pipeline!$O$2:$O$601,">="&11,Pipeline!$O$2:$O$601,"<="&14,Pipeline!$Q$2:$Q$601,"Closed Won") -> 17 | E13: =IFERROR(D13/C13,0) -> 0.083333333
B14: 15-17 (Good fit) | C14: =COUNTIFS(Pipeline!$O$2:$O$601,">="&15,Pipeline!$O$2:$O$601,"<="&17) -> 68 | D14: =COUNTIFS(Pipeline!$O$2:$O$601,">="&15,Pipeline!$O$2:$O$601,"<="&17,Pipeline!$Q$2:$Q$601,"Closed Won") -> 9 | E14: =IFERROR(D14/C14,0) -> 0.13235294
B15: 18-20 (Strong fit) | C15: =COUNTIFS(Pipeline!$O$2:$O$601,">="&18,Pipeline!$O$2:$O$601,"<="&20) -> 20 | D15: =COUNTIFS(Pipeline!$O$2:$O$601,">="&18,Pipeline!$O$2:$O$601,"<="&20,Pipeline!$Q$2:$Q$601,"Closed Won") -> 6 | E15: =IFERROR(D15/C15,0) -> 0.3

Sheet Lost Reason Analysis
A1: Lost Reason | B1: Deals Lost | C1: Revenue Lost (INR)
A2: Bad timing | B2: =COUNTIFS(Pipeline!$X$2:$X$601,A2) -> 10 | C2: =SUMIFS(Pipeline!$R$2:$R$601,Pipeline!$X$2:$X$601,A2) -> 7536000
A3: Budget too high | B3: =COUNTIFS(Pipeline!$X$2:$X$601,A3) -> 23 | C3: =SUMIFS(Pipeline!$R$2:$R$601,Pipeline!$X$2:$X$601,A3) -> 16668000
A4: Chose competitor | B4: =COUNTIFS(Pipeline!$X$2:$X$601,A4) -> 32 | C4: =SUMIFS(Pipeline!$R$2:$R$601,Pipeline!$X$2:$X$601,A4) -> 26354000
A5: Feature gap | B5: =COUNTIFS(Pipeline!$X$2:$X$601,A5) -> 12 | C5: =SUMIFS(Pipeline!$R$2:$R$601,Pipeline!$X$2:$X$601,A5) -> 9764000
A6: No decision / went dark | B6: =COUNTIFS(Pipeline!$X$2:$X$601,A6) -> 28 | C6: =SUMIFS(Pipeline!$R$2:$R$601,Pipeline!$X$2:$X$601,A6) -> 17314000
A7: Not enough authority to buy | B7: =COUNTIFS(Pipeline!$X$2:$X$601,A7) -> 9 | C7: =SUMIFS(Pipeline!$R$2:$R$601,Pipeline!$X$2:$X$601,A7) -> 5117000
